PausingIndex/PausingIndex.py
PausingIndex/__init__.py
PausingIndex/__main__.py
PausingIndex/_version.py
PausingIndex-1.0.dist-info/LICENSE
PausingIndex-1.0.dist-info/METADATA
PausingIndex-1.0.dist-info/WHEEL
PausingIndex-1.0.dist-info/entry_points.txt
PausingIndex-1.0.dist-info/top_level.txt
PausingIndex-1.0.dist-info/RECORD
